LICENSE
MANIFEST.in
README.md
setup.py
libbaihanupython/__init__.py
libbaihanupython/github_api.py
libbaihanupython.egg-info/PKG-INFO
libbaihanupython.egg-info/SOURCES.txt
libbaihanupython.egg-info/dependency_links.txt
libbaihanupython.egg-info/not-zip-safe
libbaihanupython.egg-info/requires.txt
libbaihanupython.egg-info/top_level.txt